Metadata-Version: 1.0
Name: spentalkux
Version: 13.37
Summary: I dare you to import this
Home-page: UNKNOWN
Author: UNKNOWN
Author-email: UNKNOWN
License: UNKNOWN
Platform: UNKNOWN
